odoo/addons/widget_list_limit_cell/README.rst
odoo/addons/widget_list_limit_cell/__init__.py
odoo/addons/widget_list_limit_cell/__manifest__.py
odoo/addons/widget_list_limit_cell/static/description/icon.png
odoo/addons/widget_list_limit_cell/static/src/css/font-awesome.min.css
odoo/addons/widget_list_limit_cell/static/src/css/list_renderer.css
odoo/addons/widget_list_limit_cell/static/src/fonts/FontAwesome.otf
odoo/addons/widget_list_limit_cell/static/src/fonts/fontawesome-webfont.eot
odoo/addons/widget_list_limit_cell/static/src/fonts/fontawesome-webfont.svg
odoo/addons/widget_list_limit_cell/static/src/fonts/fontawesome-webfont.ttf
odoo/addons/widget_list_limit_cell/static/src/fonts/fontawesome-webfont.woff
odoo/addons/widget_list_limit_cell/static/src/fonts/fontawesome-webfont.woff2
odoo/addons/widget_list_limit_cell/static/src/js/list_renderer.js
odoo/addons/widget_list_limit_cell/views/widget_list_limit_cell_view.xml
odoo12_addon_widget_list_limit_cell-12.0.0.1.0.dist-info/METADATA
odoo12_addon_widget_list_limit_cell-12.0.0.1.0.dist-info/WHEEL
odoo12_addon_widget_list_limit_cell-12.0.0.1.0.dist-info/top_level.txt
odoo12_addon_widget_list_limit_cell-12.0.0.1.0.dist-info/RECORD
